ha_services/__init__.py
ha_services/__main__.py
ha_services/constants.py
ha_services/example.py
ha_services/exceptions.py
ha_services/cli_app/__init__.py
ha_services/cli_app/demo.py
ha_services/cli_app/settings.py
ha_services/cli_app/shell_completion.py
ha_services/cli_app/systemd.py
ha_services/cli_app/update_readme_history.py
ha_services/cli_app/wifi_info.py
ha_services/cli_dev/__init__.py
ha_services/cli_dev/code_style.py
ha_services/cli_dev/packaging.py
ha_services/cli_dev/shell_completion.py
ha_services/cli_dev/testing.py
ha_services/cli_dev/update_ha_data.py
ha_services/cli_dev/update_readme_history.py
ha_services/ha_data/__init__.py
ha_services/ha_data/collect_ha_data.py
ha_services/ha_data/data_sensors.py
ha_services/ha_data/validators.py
ha_services/ha_data/tests/__init__.py
ha_services/ha_data/tests/test_validators.py
ha_services/mqtt4homeassistant/__init__.py
ha_services/mqtt4homeassistant/data_classes.py
ha_services/mqtt4homeassistant/device.py
ha_services/mqtt4homeassistant/mqtt.py
ha_services/mqtt4homeassistant/components/__init__.py
ha_services/mqtt4homeassistant/components/binary_sensor.py
ha_services/mqtt4homeassistant/components/select.py
ha_services/mqtt4homeassistant/components/sensor.py
ha_services/mqtt4homeassistant/components/switch.py
ha_services/mqtt4homeassistant/components/tests/__init__.py
ha_services/mqtt4homeassistant/components/tests/test_select.py
ha_services/mqtt4homeassistant/components/tests/test_sensor.py
ha_services/mqtt4homeassistant/components/tests/test_switch.py
ha_services/mqtt4homeassistant/mocks/__init__.py
ha_services/mqtt4homeassistant/mocks/mqtt_client_mock.py
ha_services/mqtt4homeassistant/mocks/psutil_mock.py
ha_services/mqtt4homeassistant/system_info/__init__.py
ha_services/mqtt4homeassistant/system_info/cpu.py
ha_services/mqtt4homeassistant/system_info/memory.py
ha_services/mqtt4homeassistant/system_info/netstat.py
ha_services/mqtt4homeassistant/system_info/temperatures.py
ha_services-2.15.0.dist-info/METADATA
ha_services-2.15.0.dist-info/WHEEL
ha_services-2.15.0.dist-info/entry_points.txt
ha_services-2.15.0.dist-info/RECORD
