Metadata-Version: 2.4
Name: ha_services
Version: 2.15.0
Summary: Helpers to send periodic information via MQTT to Home Assistant
Project-URL: Documentation, https://github.com/jedie/ha_services
Project-URL: Source, https://github.com/jedie/ha_services
Author-email: Jens Diemer <github@jensdiemer.de>
License: GPL-3.0-or-later
Requires-Python: >=3.11
Requires-Dist: cli-base-utilities>=0.18.0
Requires-Dist: frozendict
Requires-Dist: msgspec
Requires-Dist: paho-mqtt
Requires-Dist: psutil
Requires-Dist: rich
Requires-Dist: tomlkit
Requires-Dist: tyro
